CHANGELOG.rst
CONTRIBUTIONS.rst
LICENSE.txt
MANIFEST.in
README.rst
pyproject.toml
setup.py
docs/Makefile
docs/source/api_doc.rst
docs/source/changelog.rst
docs/source/conf.py
docs/source/contact.rst
docs/source/development.rst
docs/source/download.rst
docs/source/index.rst
docs/source/license.rst
docs/source/methods.rst
docs/source/publications.rst
docs/source/sitemap.rst
docs/source/tutorials.rst
docs/source/_static/default.css
docs/source/_static/logo.png
docs/source/_static/logo.psd
docs/source/_templates/layout.html
docs/source/api/climate/climate_data.rst
docs/source/api/climate/climate_network.rst
docs/source/api/climate/coupled_climate_network.rst
docs/source/api/climate/coupled_tsonis.rst
docs/source/api/climate/eventseries_climatenetwork.rst
docs/source/api/climate/havlin.rst
docs/source/api/climate/hilbert.rst
docs/source/api/climate/map_plots.rst
docs/source/api/climate/mutual_info.rst
docs/source/api/climate/partial_correlation.rst
docs/source/api/climate/rainfall.rst
docs/source/api/climate/spearman.rst
docs/source/api/climate/tsonis.rst
docs/source/api/core/data.rst
docs/source/api/core/geo_grid.rst
docs/source/api/core/geo_network.rst
docs/source/api/core/grid.rst
docs/source/api/core/interacting_networks.rst
docs/source/api/core/netcdf_dictionary.rst
docs/source/api/core/network.rst
docs/source/api/core/resistive_network.rst
docs/source/api/core/spatial_network.rst
docs/source/api/eventseries/event_series.rst
docs/source/api/funcnet/coupling_analysis.rst
docs/source/api/funcnet/coupling_analysis_pure_python.rst
docs/source/api/timeseries/cross_recurrence_plot.rst
docs/source/api/timeseries/inter_system_recurrence_network.rst
docs/source/api/timeseries/joint_recurrence_network.rst
docs/source/api/timeseries/joint_recurrence_plot.rst
docs/source/api/timeseries/recurrence_network.rst
docs/source/api/timeseries/recurrence_plot.rst
docs/source/api/timeseries/surrogates.rst
docs/source/api/timeseries/visibility_graph.rst
docs/source/api/utils/mpi.rst
src/pyunicorn.egg-info/PKG-INFO
src/pyunicorn.egg-info/SOURCES.txt
src/pyunicorn.egg-info/dependency_links.txt
src/pyunicorn.egg-info/requires.txt
src/pyunicorn.egg-info/top_level.txt
