Metadata-Version: 2.4
Name: pyunicorn
Version: 0.9.0
Summary: Unified complex network and recurrence analysis toolbox
Author-email: "Jonathan F. Donges" <donges@pik-potsdam.de>
Maintainer-email: Fritz Kühlein <fritzku@pik-potsdam.de>, Boyan Beronov <beronov@cs.ubc.ca>
License-Expression: BSD-3-Clause
Project-URL: Homepage, https://www.pik-potsdam.de/members/donges/software-2/software
Project-URL: Documentation, http://www.pik-potsdam.de/~donges/pyunicorn/
Project-URL: Repository, https://github.com/pik-copan/pyunicorn
Project-URL: Changelog, https://github.com/pik-copan/pyunicorn/blob/master/CHANGELOG.rst
Project-URL: Issues, https://github.com/pik-copan/pyunicorn/issues
Keywords: complex network,nonlinear time series analysis,climate network,recurrence plot,surrogate model
Classifier: Development Status :: 5 - Production/Stable
Classifier: Environment :: Console
Classifier: Intended Audience :: Developers
Classifier: Intended Audience :: Science/Research
Classifier: Topic :: Scientific/Engineering :: GIS
Classifier: Topic :: Scientific/Engineering :: Information Analysis
Classifier: Topic :: Scientific/Engineering :: Mathematics
Classifier: Topic :: Scientific/Engineering :: Physics
Classifier: Natural Language :: English
Classifier: Operating System :: OS Independent
Classifier: Programming Language :: Python :: 3 :: Only
Classifier: Programming Language :: Python :: 3.10
Classifier: Programming Language :: Python :: 3.11
Classifier: Programming Language :: Python :: 3.12
Classifier: Programming Language :: Python :: 3.13
Classifier: Programming Language :: Python :: 3.14
Classifier: Framework :: Pytest
Requires-Python: >=3.10
License-File: LICENSE.txt
Requires-Dist: numpy>=1.24
Requires-Dist: scipy>=1.10
Requires-Dist: igraph>=0.11
Requires-Dist: h5netcdf[h5py]>=1.8
Requires-Dist: tqdm>=4.66
Dynamic: license-file
